main.py
codo_api-1.0.0.dist-info/LICENSE
codo_api-1.0.0.dist-info/METADATA
codo_api-1.0.0.dist-info/WHEEL
codo_api-1.0.0.dist-info/top_level.txt
codo_api-1.0.0.dist-info/RECORD
