Metadata-Version: 2.2
Name: codo-api
Version: 1.0.0
Summary: (C)ompute (O)perations in (D)ependency (O)rder
License-File: LICENSE
